[{"id":"68ace89fbddf7","timestamp":"2025-08-25 22:50:07","data":{"user_id":1,"amount":25,"type":"place","selection":[1,7],"color":"linear-gradient(180deg, #FF170F 0%, #FF005E 100%)","time":"01:50:04"}},{"id":"68ace89f53994","timestamp":"2025-08-25 22:50:07","data":{"user_id":1,"amount":25,"type":"place","selection":[1,4],"color":"linear-gradient(180deg, #FF170F 0%, #FF005E 100%)","time":"01:50:04"}},{"id":"68ace89ed9073","timestamp":"2025-08-25 22:50:06","data":{"user_id":1,"amount":25,"type":"place","selection":[1,5],"color":"linear-gradient(180deg, #FF170F 0%, #FF005E 100%)","time":"01:50:04"}},{"id":"68ace89e6fb86","timestamp":"2025-08-25 22:50:06","data":{"user_id":1,"amount":25,"type":"place","selection":[1,3],"color":"linear-gradient(180deg, #FF170F 0%, #FF005E 100%)","time":"01:50:04"}},{"id":"68ace89e0cae1","timestamp":"2025-08-25 22:50:06","data":{"user_id":1,"amount":25,"type":"place","selection":[1,6],"color":"linear-gradient(180deg, #FF170F 0%, #FF005E 100%)","time":"01:50:04"}},{"id":"68ace89d9dc41","timestamp":"2025-08-25 22:50:05","data":{"user_id":1,"amount":25,"type":"place","selection":[1,2],"color":"linear-gradient(180deg, #FF170F 0%, #FF005E 100%)","time":"01:50:04"}},{"id":"68ace89d304ad","timestamp":"2025-08-25 22:50:05","data":{"user_id":1,"amount":25,"type":"place","selection":[1,1],"color":"linear-gradient(180deg, #FF170F 0%, #FF005E 100%)","time":"01:50:04"}},{"id":"68ace88811194","timestamp":"2025-08-25 22:49:44","data":{"user_id":1,"amount":25,"type":"place","selection":[7,1],"color":"linear-gradient(180deg, #FF170F 0%, #FF005E 100%)","time":"01:49:40"}},{"id":"68ace88793d66","timestamp":"2025-08-25 22:49:43","data":{"user_id":1,"amount":25,"type":"place","selection":[6,1],"color":"linear-gradient(180deg, #FF170F 0%, #FF005E 100%)","time":"01:49:40"}},{"id":"68ace88726842","timestamp":"2025-08-25 22:49:43","data":{"user_id":1,"amount":25,"type":"place","selection":[4,1],"color":"linear-gradient(180deg, #FF170F 0%, #FF005E 100%)","time":"01:49:40"}}]