[{"id":"68a5bdb4b1768","timestamp":"2025-08-20 12:21:08","data":{"user_id":1,"amount":25,"type":"place","selection":[7,4],"color":"linear-gradient(180deg, #FF170F 0%, #FF005E 100%)","time":"15:21:08"}},{"id":"68a5bda15f415","timestamp":"2025-08-20 12:20:49","data":{"user_id":1,"amount":25,"type":"place","selection":[7,4],"color":"linear-gradient(180deg, #FF170F 0%, #FF005E 100%)","time":"15:20:49"}},{"id":"68a5bd9cef1f6","timestamp":"2025-08-20 12:20:44","data":{"user_id":1,"amount":25,"type":"place","selection":[7,4],"color":"linear-gradient(180deg, #FF170F 0%, #FF005E 100%)","time":"15:20:44"}},{"id":"68a5bd860b3c8","timestamp":"2025-08-20 12:20:22","data":{"user_id":1,"amount":25,"type":"place","selection":[7,4],"color":"linear-gradient(180deg, #FF170F 0%, #FF005E 100%)","time":"15:20:21"}},{"id":"68a5bc49041f6","timestamp":"2025-08-20 12:15:05","data":{"user_id":1,"amount":25,"type":"place","selection":[7,4],"color":"linear-gradient(180deg, #FF170F 0%, #FF005E 100%)","time":"15:15:04"}},{"id":"68a5bc3e28bff","timestamp":"2025-08-20 12:14:54","data":{"user_id":1,"amount":25,"type":"place","selection":[7,4],"color":"linear-gradient(180deg, #FF170F 0%, #FF005E 100%)","time":"15:14:53"}},{"id":"68a5bc2fee62f","timestamp":"2025-08-20 12:14:39","data":{"user_id":1,"amount":25,"type":"place","selection":[7,4],"color":"linear-gradient(180deg, #FF170F 0%, #FF005E 100%)","time":"15:14:39"}},{"id":"68a5bc1da85a9","timestamp":"2025-08-20 12:14:21","data":{"user_id":1,"amount":25,"type":"place","selection":[7,4],"color":"linear-gradient(180deg, #FF170F 0%, #FF005E 100%)","time":"15:14:21"}},{"id":"68a5bc09f22c5","timestamp":"2025-08-20 12:14:01","data":{"user_id":1,"amount":25,"type":"place","selection":[7,4],"color":"linear-gradient(180deg, #FF170F 0%, #FF005E 100%)","time":"15:14:01"}},{"id":"68a5bc03001bd","timestamp":"2025-08-20 12:13:55","data":{"user_id":1,"amount":25,"type":"place","selection":[7,4],"color":"linear-gradient(180deg, #FF170F 0%, #FF005E 100%)","time":"15:13:54"}}]