[{"id":"68aa42bb93879","timestamp":"2025-08-23 22:37:47","results":[{"position":null,"color":"#FFFF00"},{"position":2,"color":"#FFA500"},{"position":null,"color":"#8B0000"},{"position":null,"color":"#0000FF"},{"position":null,"color":"#FF0000"},{"position":null,"color":"#800080"},{"position":1,"color":"#00FF00"}]},{"id":"68aa42b728cac","timestamp":"2025-08-23 22:37:43","results":[{"position":null,"color":"#FFFF00"},{"position":null,"color":"#FFA500"},{"position":2,"color":"#8B0000"},{"position":null,"color":"#0000FF"},{"position":null,"color":"#FF0000"},{"position":1,"color":"#800080"},{"position":null,"color":"#00FF00"}]},{"id":"68aa42a3dcd7b","timestamp":"2025-08-23 22:37:23","results":[{"position":4,"color":"#FFFF00"},{"position":3,"color":"#FFA500"},{"position":2,"color":"#8B0000"},{"position":6,"color":"#0000FF"},{"position":1,"color":"#FF0000"},{"position":7,"color":"#800080"},{"position":5,"color":"#00FF00"}]},{"id":"68aa42a3b0204","timestamp":"2025-08-23 22:37:23","results":[{"position":4,"color":"#FFFF00"},{"position":3,"color":"#FFA500"},{"position":2,"color":"#8B0000"},{"position":6,"color":"#0000FF"},{"position":1,"color":"#FF0000"},{"position":7,"color":"#800080"},{"position":5,"color":"#00FF00"}]},{"id":"68aa4274c4b1b","timestamp":"2025-08-23 22:36:36","results":[{"position":null,"color":"#FFFF00"},{"position":null,"color":"#FFA500"},{"position":null,"color":"#8B0000"},{"position":2,"color":"#0000FF"},{"position":1,"color":"#FF0000"},{"position":null,"color":"#800080"},{"position":3,"color":"#00FF00"}]}]